wtforms_html5.py
wtforms_html5-0.6.1.dist-info/LICENSE.txt
wtforms_html5-0.6.1.dist-info/METADATA
wtforms_html5-0.6.1.dist-info/WHEEL
wtforms_html5-0.6.1.dist-info/top_level.txt
wtforms_html5-0.6.1.dist-info/RECORD
