Metadata-Version: 2.1
Name: wtforms-html5
Version: 0.6.1
Summary: Generates render keywords for widgets of WTForms HTML5 fields.
Home-page: https://github.com/brutus/wtforms-html5/
Author: Brutus
Author-email: brutus.dmc@googlemail.com
License: GNU GPLv3
Platform: UNKNOWN
Classifier: License :: OSI Approved :: GNU General Public License (GPL)
Classifier: Operating System :: OS Independent
Classifier: Programming Language :: Python
Classifier: Development Status :: 4 - Beta
Classifier: Environment :: Web Environment
Classifier: Intended Audience :: Developers
Classifier: Natural Language :: English
Classifier: Topic :: Internet :: WWW/HTTP
License-File: LICENSE.txt
